CHANGELOG.md
COPYING
MANIFEST.in
README.md
VERSION
config.sample.yaml
setup.cfg
setup.py
version.sh
contrib/migrate-tenants
contrib/migrate-users
odm/__init__.py
odm/cli.py
odm/googledriveclient.py
odm/inkml.py
odm/ms365.py
odm/onedriveclient.py
odm/onedrivesession.py
odm/quickxorhash.py
odm/sharepointsession.py
odm/util.py
odm/version.py
odm.egg-info/PKG-INFO
odm.egg-info/SOURCES.txt
odm.egg-info/dependency_links.txt
odm.egg-info/entry_points.txt
odm.egg-info/not-zip-safe
odm.egg-info/requires.txt
odm.egg-info/top_level.txt
odm/libexec/__init__.py
odm/libexec/gdm_filetree.py
odm/libexec/odm_adhoc.py
odm/libexec/odm_filetree.py
odm/libexec/odm_group.py
odm/libexec/odm_list.py
odm/libexec/odm_sharepoint.py
odm/libexec/odm_site.py
odm/libexec/odm_tenant.py
odm/libexec/odm_test.py
odm/libexec/odm_test2.py
odm/libexec/odm_user.py
odm/libexec/odm_version.py
odm/libexec/wrapper.py