Metadata-Version: 2.1
Name: odm
Version: 2.0.0
Summary: Storage Magic
Home-page: https://github.com/UMCollab/ODM
Author: Ezekiel Hendrickson
Author-email: ezekielh@umich.edu
License: MIT
Platform: UNKNOWN
